{
  "heading-xl": [
    {
      "name": "heading-xl",
      "value": 450
    },
    {
      "name": "heading-xl",
      "value": 32
    },
    {
      "name": "heading-xl",
      "value": 44
    }
  ],
  "heading-l": [
    {
      "name": "heading-l",
      "value": 450
    },
    {
      "name": "heading-l",
      "value": 28
    },
    {
      "name": "heading-l",
      "value": 40
    }
  ],
  "heading-m": [
    {
      "name": "heading-m",
      "value": 450
    },
    {
      "name": "heading-m",
      "value": 24
    },
    {
      "name": "heading-m",
      "value": 32
    }
  ],
  "heading-s": [
    {
      "name": "heading-s",
      "value": 450
    },
    {
      "name": "heading-s",
      "value": 20
    },
    {
      "name": "heading-s",
      "value": 28
    }
  ],
  "heading-xs": [
    {
      "name": "heading-xs",
      "value": 450
    },
    {
      "name": "heading-xs",
      "value": 16
    },
    {
      "name": "heading-xs",
      "value": 24
    }
  ],
  "heading-2xs": [
    {
      "name": "heading-2xs",
      "value": 450
    },
    {
      "name": "heading-2xs",
      "value": 14
    },
    {
      "name": "heading-2xs",
      "value": 20
    }
  ],
  "detail-book-m": [
    {
      "name": "detail-book-m",
      "value": 450
    },
    {
      "name": "detail-book-m",
      "value": 16
    },
    {
      "name": "detail-book-m",
      "value": 20
    }
  ],
  "detail-book-s": [
    {
      "name": "detail-book-s",
      "value": 450
    },
    {
      "name": "detail-book-s",
      "value": 14
    },
    {
      "name": "detail-book-s",
      "value": 20
    }
  ],
  "detail-book-xs": [
    {
      "name": "detail-book-xs",
      "value": 450
    },
    {
      "name": "detail-book-xs",
      "value": 12
    },
    {
      "name": "detail-book-xs",
      "value": 16
    }
  ],
  "detail-regular-m": [
    {
      "name": "detail-regular-m",
      "value": 400
    },
    {
      "name": "detail-regular-m",
      "value": 16
    },
    {
      "name": "detail-regular-m",
      "value": 20
    }
  ],
  "detail-regular-s": [
    {
      "name": "detail-regular-s",
      "value": 400
    },
    {
      "name": "detail-regular-s",
      "value": 14
    },
    {
      "name": "detail-regular-s",
      "value": 20
    }
  ],
  "detail-regular-xs": [
    {
      "name": "detail-regular-xs",
      "value": 400
    },
    {
      "name": "detail-regular-xs",
      "value": 12
    },
    {
      "name": "detail-regular-xs",
      "value": 16
    }
  ],
  "body-book-l": [
    {
      "name": "body-book-l",
      "value": 450
    },
    {
      "name": "body-book-l",
      "value": 20
    },
    {
      "name": "body-book-l",
      "value": 26
    }
  ],
  "body-book-m": [
    {
      "name": "body-book-m",
      "value": 450
    },
    {
      "name": "body-book-m",
      "value": 16
    },
    {
      "name": "body-book-m",
      "value": 24
    }
  ],
  "body-book-s": [
    {
      "name": "body-book-s",
      "value": 450
    },
    {
      "name": "body-book-s",
      "value": 14
    },
    {
      "name": "body-book-s",
      "value": 20
    }
  ],
  "body-regular-l": [
    {
      "name": "body-regular-l",
      "value": 400
    },
    {
      "name": "body-regular-l",
      "value": 20
    },
    {
      "name": "body-regular-l",
      "value": 26
    }
  ],
  "body-regular-m": [
    {
      "name": "body-regular-m",
      "value": 400
    },
    {
      "name": "body-regular-m",
      "value": 16
    },
    {
      "name": "body-regular-m",
      "value": 24
    }
  ],
  "body-regular-s": [
    {
      "name": "body-regular-s",
      "value": 400
    },
    {
      "name": "body-regular-s",
      "value": 14
    },
    {
      "name": "body-regular-s",
      "value": 20
    }
  ],
  "body-italic-l": [
    {
      "name": "body-italic-l",
      "value": 400
    },
    {
      "name": "body-italic-l",
      "value": "italic"
    },
    {
      "name": "body-italic-l",
      "value": 20
    },
    {
      "name": "body-italic-l",
      "value": 26
    }
  ],
  "body-italic-m": [
    {
      "name": "body-italic-m",
      "value": 400
    },
    {
      "name": "body-italic-m",
      "value": "italic"
    },
    {
      "name": "body-italic-m",
      "value": 16
    },
    {
      "name": "body-italic-m",
      "value": 24
    }
  ],
  "body-italic-s": [
    {
      "name": "body-italic-s",
      "value": 400
    },
    {
      "name": "body-italic-s",
      "value": "italic"
    },
    {
      "name": "body-italic-s",
      "value": 14
    },
    {
      "name": "body-italic-s",
      "value": 20
    }
  ],
  "display-2xl": [
    {
      "name": "display-2xl",
      "value": 450
    },
    {
      "name": "display-2xl",
      "value": 82
    },
    {
      "name": "display-2xl",
      "value": 90
    }
  ],
  "display-xl": [
    {
      "name": "display-xl",
      "value": 450
    },
    {
      "name": "display-xl",
      "value": 64
    },
    {
      "name": "display-xl",
      "value": 72
    }
  ],
  "display-l": [
    {
      "name": "display-l",
      "value": 450
    },
    {
      "name": "display-l",
      "value": 48
    },
    {
      "name": "display-l",
      "value": 56
    }
  ],
  "display-m": [
    {
      "name": "display-m",
      "value": 450
    },
    {
      "name": "display-m",
      "value": 36
    },
    {
      "name": "display-m",
      "value": 44
    }
  ],
  "display-s": [
    {
      "name": "display-s",
      "value": 450
    },
    {
      "name": "display-s",
      "value": 32
    },
    {
      "name": "display-s",
      "value": 40
    }
  ],
  "preamble-2xl": [
    {
      "name": "preamble-2xl",
      "value": 450
    },
    {
      "name": "preamble-2xl",
      "value": 32
    },
    {
      "name": "preamble-2xl",
      "value": 40
    }
  ],
  "preamble-xl": [
    {
      "name": "preamble-xl",
      "value": 450
    },
    {
      "name": "preamble-xl",
      "value": 28
    },
    {
      "name": "preamble-xl",
      "value": 36
    }
  ],
  "preamble-l": [
    {
      "name": "preamble-l",
      "value": 450
    },
    {
      "name": "preamble-l",
      "value": 24
    },
    {
      "name": "preamble-l",
      "value": 32
    }
  ],
  "preamble-m": [
    {
      "name": "preamble-m",
      "value": 450
    },
    {
      "name": "preamble-m",
      "value": 20
    },
    {
      "name": "preamble-m",
      "value": 28
    }
  ],
  "preamble-s": [
    {
      "name": "preamble-s",
      "value": 450
    },
    {
      "name": "preamble-s",
      "value": 18
    },
    {
      "name": "preamble-s",
      "value": 26
    }
  ],
  "preamble-xs": [
    {
      "name": "preamble-xs",
      "value": 450
    },
    {
      "name": "preamble-xs",
      "value": 16
    },
    {
      "name": "preamble-xs",
      "value": 24
    }
  ]
}