[
  {"name":"shadow/s-01-color","value":"#060D1314"},
  {"name":"shadow/s-01-offsetX","value":"0px"},
  {"name":"shadow/s-01-offsetY","value":"0px"},
  {"name":"shadow/s-01-blur","value":"2px"},
  {"name":"shadow/s-01-spread","value":"0px"},
  {"name":"shadow/s-02-color","value":"transparent"},
  {"name":"shadow/s-02-offsetX","value":"0px"},
  {"name":"shadow/s-02-offsetY","value":"0px"},
  {"name":"shadow/s-02-blur","value":"0px"},
  {"name":"shadow/s-02-spread","value":"0px"},
  {"name":"shadow/m-01-color","value":"#060D131a"},
  {"name":"shadow/m-01-offsetX","value":"0px"},
  {"name":"shadow/m-01-offsetY","value":"4px"},
  {"name":"shadow/m-01-blur","value":"8px"},
  {"name":"shadow/m-01-spread","value":"-2px"},
  {"name":"shadow/m-02-color","value":"#060D130f"},
  {"name":"shadow/m-02-offsetX","value":"0px"},
  {"name":"shadow/m-02-offsetY","value":"2px"},
  {"name":"shadow/m-02-blur","value":"4px"},
  {"name":"shadow/m-02-spread","value":"-2px"},
  {"name":"shadow/l-01-color","value":"#060D1314"},
  {"name":"shadow/l-01-offsetX","value":"0px"},
  {"name":"shadow/l-01-offsetY","value":"20px"},
  {"name":"shadow/l-01-blur","value":"24px"},
  {"name":"shadow/l-01-spread","value":"-4px"},
  {"name":"shadow/l-02-color","value":"#060D1308"},
  {"name":"shadow/l-02-offsetX","value":"0px"},
  {"name":"shadow/l-02-offsetY","value":"8px"},
  {"name":"shadow/l-02-blur","value":"8px"},
  {"name":"shadow/l-02-spread","value":"-4px"},
  {"name":"shadow/xl-01-color","value":"#060D132e"},
  {"name":"shadow/xl-01-offsetX","value":"0px"},
  {"name":"shadow/xl-01-offsetY","value":"24px"},
  {"name":"shadow/xl-01-blur","value":"48px"},
  {"name":"shadow/xl-01-spread","value":"-12px"},
  {"name":"shadow/xl-02-color","value":"transparent"},
  {"name":"shadow/xl-02-offsetX","value":"0px"},
  {"name":"shadow/xl-02-offsetY","value":"0px"},
  {"name":"shadow/xl-02-blur","value":"0px"},
  {"name":"shadow/xl-02-spread","value":"0px"}
]
