{
  "sys": {
    "shadow": {
      "xs-offset-x-1": {
        "value": "0",
        "type": "float"
      },
      "xs-offset-y-1": {
        "value": "0",
        "type": "float"
      },
      "xs-blur-1": {
        "value": "1",
        "type": "float"
      },
      "xs-spread-1": {
        "value": "0",
        "type": "float"
      },
      "xs-color-1": {
        "value": "#000000",
        "type": "color"
      },
      "xs-offset-x-2": {
        "value": "0",
        "type": "float"
      },
      "xs-offset-y-2": {
        "value": "0",
        "type": "float"
      },
      "xs-blur-2": {
        "value": "1",
        "type": "float"
      },
      "xs-spread-2": {
        "value": "0",
        "type": "float"
      },
      "xs-color-2": {
        "value": "#000000",
        "type": "color"
      },
      "s-offset-x-1": {
        "value": "0",
        "type": "float"
      },
      "s-offset-y-1": {
        "value": "1",
        "type": "float"
      },
      "s-blur-1": {
        "value": "3",
        "type": "float"
      },
      "s-spread-1": {
        "value": "0",
        "type": "float"
      },
      "s-color-1": {
        "value": "#000000",
        "type": "color"
      },
      "s-offset-x-2": {
        "value": "0",
        "type": "float"
      },
      "s-offset-y-2": {
        "value": "1",
        "type": "float"
      },
      "s-blur-2": {
        "value": "2",
        "type": "float"
      },
      "s-spread-2": {
        "value": "0",
        "type": "float"
      },
      "s-color-2": {
        "value": "#000000",
        "type": "color"
      },
      "m-offset-x-1": {
        "value": "0",
        "type": "float"
      },
      "m-offset-y-1": {
        "value": "4",
        "type": "float"
      },
      "m-blur-1": {
        "value": "8",
        "type": "float"
      },
      "m-spread-1": {
        "value": "-2",
        "type": "float"
      },
      "m-color-1": {
        "value": "#000000",
        "type": "color"
      },
      "m-offset-x-2": {
        "value": "0",
        "type": "float"
      },
      "m-offset-y-2": {
        "value": "2",
        "type": "float"
      },
      "m-blur-2": {
        "value": "4",
        "type": "float"
      },
      "m-spread-2": {
        "value": "-2",
        "type": "float"
      },
      "m-color-2": {
        "value": "#000000",
        "type": "color"
      },
      "l-offset-x-1": {
        "value": "0",
        "type": "float"
      },
      "l-offset-y-1": {
        "value": "12",
        "type": "float"
      },
      "l-blur-1": {
        "value": "16",
        "type": "float"
      },
      "l-spread-1": {
        "value": "-4",
        "type": "float"
      },
      "l-color-1": {
        "value": "#000000",
        "type": "color"
      },
      "l-offset-x-2": {
        "value": "0",
        "type": "float"
      },
      "l-offset-y-2": {
        "value": "4",
        "type": "float"
      },
      "l-blur-2": {
        "value": "6",
        "type": "float"
      },
      "l-spread-2": {
        "value": "-2",
        "type": "float"
      },
      "l-color-2": {
        "value": "#000000",
        "type": "color"
      },
      "xl-offset-x-1": {
        "value": "0",
        "type": "float"
      },
      "xl-offset-y-1": {
        "value": "20",
        "type": "float"
      },
      "xl-blur-1": {
        "value": "24",
        "type": "float"
      },
      "xl-spread-1": {
        "value": "-4",
        "type": "float"
      },
      "xl-color-1": {
        "value": "#000000",
        "type": "color"
      },
      "xl-offset-x-2": {
        "value": "0",
        "type": "float"
      },
      "xl-offset-y-2": {
        "value": "8",
        "type": "float"
      },
      "xl-blur-2": {
        "value": "8",
        "type": "float"
      },
      "xl-spread-2": {
        "value": "-4",
        "type": "float"
      },
      "xl-color-2": {
        "value": "#000000",
        "type": "color"
      }
    }
  }
}
