{
  "cacheItemsMap": {
    "badge/todo.md": {
      "document": {
        "_id": "badge/todo.md",
        "_raw": {
          "sourceFilePath": "badge/todo.md",
          "sourceFileName": "todo.md",
          "sourceFileDir": "badge",
          "contentType": "markdown",
          "flattenedPath": "badge/todo"
        },
        "type": "Todo"
      },
      "documentHash": "1707419895017",
      "hasWarnings": false,
      "documentTypeName": "Todo"
    },
    "button/todo.md": {
      "document": {
        "_id": "button/todo.md",
        "_raw": {
          "sourceFilePath": "button/todo.md",
          "sourceFileName": "todo.md",
          "sourceFileDir": "button",
          "contentType": "markdown",
          "flattenedPath": "button/todo"
        },
        "type": "Todo"
      },
      "documentHash": "1707419895017",
      "hasWarnings": false,
      "documentTypeName": "Todo"
    },
    "dropdown/todo.md": {
      "document": {
        "_id": "dropdown/todo.md",
        "_raw": {
          "sourceFilePath": "dropdown/todo.md",
          "sourceFileName": "todo.md",
          "sourceFileDir": "dropdown",
          "contentType": "markdown",
          "flattenedPath": "dropdown/todo"
        },
        "type": "Todo"
      },
      "documentHash": "1702471554751",
      "hasWarnings": false,
      "documentTypeName": "Todo"
    },
    "icon/todo.md": {
      "document": {
        "_id": "icon/todo.md",
        "_raw": {
          "sourceFilePath": "icon/todo.md",
          "sourceFileName": "todo.md",
          "sourceFileDir": "icon",
          "contentType": "markdown",
          "flattenedPath": "icon/todo"
        },
        "type": "Todo"
      },
      "documentHash": "1707419895022",
      "hasWarnings": false,
      "documentTypeName": "Todo"
    },
    "tooltip/todo.md": {
      "document": {
        "_id": "tooltip/todo.md",
        "_raw": {
          "sourceFilePath": "tooltip/todo.md",
          "sourceFileName": "todo.md",
          "sourceFileDir": "tooltip",
          "contentType": "markdown",
          "flattenedPath": "tooltip/todo"
        },
        "type": "Todo"
      },
      "documentHash": "1707419895023",
      "hasWarnings": false,
      "documentTypeName": "Todo"
    }
  }
}
